[
  {
    "id": 1732455865661,
    "text": "123",
    "completed": false
  },
  {
    "id": 1732455872623,
    "text": "выавыа",
    "completed": false
  },
  {
    "id": 1732475290813,
    "text": "34",
    "completed": false
  },
  {
    "id": 1732475413578,
    "text": "ВЫАВЫА",
    "completed": false
  },
  {
    "id": 1732477827686,
    "text": "ibat",
    "completed": false
  },
  {
    "id": 1732705925663,
    "text": "saasdasd",
    "completed": false
  },
  {
    "id": 1732806163007,
    "text": "dvxvcx",
    "completed": false
  }
]